{
  "aor": 0.0033475872093023263,
  "aqi": 0.0033593796511627904,
  "bids_meta": {
    "EchoTime": 0.026,
    "FlipAngle": 50,
    "RepetitionTime": 1,
    "TaskName": "DNMS",
    "dataset": "ds001576",
    "modality": "bold",
    "run_id": 3,
    "subject_id": "18",
    "task_id": "dnms"
  },
  "dummy_trs": 6,
  "dvars_nstd": 27.21837904,
  "dvars_std": 1.3510279794460647,
  "dvars_vstd": 1.0428059007871715,
  "efc": 0.6608470752833211,
  "fber": 155.41844177246094,
  "fd_mean": 0.08462024038387088,
  "fd_num": 4,
  "fd_perc": 1.1627906976744187,
  "fwhm_avg": 3.186108482729931,
  "fwhm_x": 2.790668652557876,
  "fwhm_y": 3.245516795631917,
  "fwhm_z": 3.5221400000000003,
  "gcor": 0.0252609,
  "gsr_x": 0.04091613367199898,
  "gsr_y": 0.03287336602807045,
  "provenance": {
    "md5sum": "ea04de03c9689a5c7acb6554d1646ff5",
    "settings": {
      "fd_thres": 0.2,
      "testing": false
    },
    "software": "mriqc",
    "version": "22.0.6",
    "webapi_port": null,
    "webapi_url": "https://mriqc.nimh.nih.gov/api/v1"
  },
  "size_t": 344,
  "size_x": 76,
  "size_y": 76,
  "size_z": 44,
  "snr": 2.152953210779978,
  "spacing_tr": 1.0,
  "spacing_x": 2.526315689086914,
  "spacing_y": 2.526315689086914,
  "spacing_z": 2.5,
  "summary_bg_k": 17.773034897837885,
  "summary_bg_mad": 27.1393790585957,
  "summary_bg_mean": 77.13152313232422,
  "summary_bg_median": 36.86046600341797,
  "summary_bg_n": 113823.0,
  "summary_bg_p05": 15.857558250427246,
  "summary_bg_p95": 280.6642425537105,
  "summary_bg_stdv": 103.66336822509766,
  "summary_fg_k": 1.6931264927965435,
  "summary_fg_mad": 206.92858969017658,
  "summary_fg_mean": 570.0586547851562,
  "summary_fg_median": 515.534912109375,
  "summary_fg_n": 81998.0,
  "summary_fg_p05": 284.1286193847656,
  "summary_fg_p95": 1042.5797912597657,
  "summary_fg_stdv": 239.45330810546875,
  "tsnr": 60.82603047718294
}