{
  "aor": 0.002926475644699141,
  "aqi": 0.008480937335243553,
  "bids_meta": {
    "EchoTime": 0.026,
    "FlipAngle": 50,
    "RepetitionTime": 1,
    "TaskName": "DNMS",
    "dataset": "ds001576",
    "modality": "bold",
    "run_id": 5,
    "subject_id": "05",
    "task_id": "dnms"
  },
  "dummy_trs": 1,
  "dvars_nstd": 28.41326170390802,
  "dvars_std": 0.9835310327011502,
  "dvars_vstd": 0.9219979515517243,
  "efc": 0.6346195669245328,
  "fber": 305.2880554199219,
  "fd_mean": 0.2633805112401071,
  "fd_num": 137,
  "fd_perc": 39.25501432664756,
  "fwhm_avg": 3.2076896372046058,
  "fwhm_x": 2.8278334457013385,
  "fwhm_y": 3.33646346591248,
  "fwhm_z": 3.4587719999999997,
  "gcor": 0.0443709,
  "gsr_x": -0.00488079059869051,
  "gsr_y": 0.06389100849628448,
  "provenance": {
    "md5sum": "1ee4e8d2f9263cc2964317de7483138f",
    "settings": {
      "fd_thres": 0.2,
      "testing": false
    },
    "software": "mriqc",
    "version": "22.0.6",
    "webapi_port": null,
    "webapi_url": "https://mriqc.nimh.nih.gov/api/v1"
  },
  "size_t": 349,
  "size_x": 76,
  "size_y": 76,
  "size_z": 44,
  "snr": 2.4452248556262983,
  "spacing_tr": 1.0,
  "spacing_x": 2.526315689086914,
  "spacing_y": 2.526315689086914,
  "spacing_z": 2.5,
  "summary_bg_k": 33.18348052505217,
  "summary_bg_mad": 21.172748390794226,
  "summary_bg_mean": 62.155216217041016,
  "summary_bg_median": 29.332378387451172,
  "summary_bg_n": 121995.0,
  "summary_bg_p05": 14.008596420288086,
  "summary_bg_p95": 207.6710617065425,
  "summary_bg_stdv": 89.1661148071289,
  "summary_fg_k": 1.3210325593692431,
  "summary_fg_mad": 205.5294879109487,
  "summary_fg_mean": 602.1038208007812,
  "summary_fg_median": 557.4742431640625,
  "summary_fg_n": 78064.0,
  "summary_fg_p05": 316.6938507080078,
  "summary_fg_p95": 1036.7977783203119,
  "summary_fg_stdv": 227.9833984375,
  "tsnr": 37.91295264707878
}